{
  "basics": {
    "name": "Gilang Gumilar",
    "label": "Software Engineer",
    "picture": "https://avatars3.githubusercontent.com/u/15117750",
    "email": "gilangmlr@gmail.com",
    "phone": "(+62) 813-8658-5941",
    "website": "https://gilangmlr.github.io/",
    "summary": "Passionate Software Engineer. Life-long learner. Love to learn many things.",
    "location": {
      "address": "BPA I DD 18, Pagedangan",
      "postalCode": "15339",
      "city": "Tangerang",
      "countryCode": "ID",
      "region": "Banten"
    },
    "profiles": [
      {
        "network": "LinkedIn",
        "username": "gilangmlr",
        "url": "https://linkedin.com/in/gilangmlr"
      },
      {
        "network": "GitHub",
        "username": "gilangmlr",
        "url": "https://github.com/gilangmlr"
      }
    ]
  },
  "work": [
    {
      "company": "PT. Bukalapak.com",
      "position": "Part-time Front-end Engineer",
      "website": "https://www.bukalapak.com/",
      "startDate": "2018-03-07",
      "summary": "Bukalapak is one of the leading online marketplace in Indonesia and a Unicorn company, owned and run by PT. Bukalapak.",
      "highlights": [
        "Created Bukalapak's internal dashboard admin for Core Trust and Safety. (Vue.js, VueX, Vuetify, Express.js)",
        "Created Bukalapak's Vue UI Component Library. (Vue.js, Storybook, Jest, SASS)",
        "Maintained Bukalapak's mobile web (Vue.js, VueX), Bukalapak's centralized front-end documentations (Express.js), Bukalapak's front-end data tracking utility (JavaScript)."
      ]
    },
    {
      "company": "GoriTax",
      "position": "Part-time Full Stack Engineer",
      "website": "https://www.gori-tax.id/",
      "startDate": "2019-01-07",
      "endDate": "2019-04-07",
      "summary": "GoriTax is a curated tax and accounting experts as a service.",
      "highlights": [
        "Designed the database (SQL, PostgreSQL), created the back-end with a RESTful API (Python, Django, Django REST framework), and created the infrastructure (Docker, Kubernetes, AWS, Kops, Gitlab CI/CD).",
        "Created the front-end with a front-end engineer. (ReactJS, Redux, Material-UI)"
      ]
    },
    {
      "company": "PT. Bukalapak.com",
      "position": "Front-end Engineer Intern",
      "website": "https://www.bukalapak.com/",
      "startDate": "2017-12-27",
      "endDate": "2018-03-07",
      "summary": "Bukalapak is one of the leading online marketplace in Indonesia and a Unicorn company, owned and run by PT. Bukalapak.",
      "highlights": [
        "Rewrote the product detail page on mobile web using Vue.js and Bukalapak's RESTful API. (Vue.js)"
      ]
    },
    {
      "company": "Computer Science Faculty of Universitas Indonesia",
      "position": "Teaching Assistant",
      "website": "https://www.cs.ui.ac.id/",
      "startDate": "2017-09-01",
      "endDate": "2017-12-01",
      "summary": "Assisted the lecturer of Web Design and Programming (International Class) course",
      "highlights": [
        "Assisted students in lab sessions.",
        "Created weekly lab tutorials with other assistants."
      ]
    },
    {
      "company": "Jojonomic Pte. Ltd.",
      "position": "Web Developer Intern",
      "website": "https://jojonomic.com/",
      "startDate": "2017-01-02",
      "endDate": "2017-02-01",
      "summary": "Jojonomic provides services that can easily control company expenses with Real Time Approval.",
      "highlights": [
        "Developed the web app features using HTML, CSS, JS."
      ]
    }
  ],
  "volunteer": [
    {
      "organization": "freeCodeCamp",
      "position": "Student",
      "website": "https://www.freeCodeCamp.org/gilangmlr",
      "startDate": "2016-06-01",
      "endDate": "2016-09-01",
      "summary": "freeCodeCamp is a nonprofit organization that consists of an interactive learning web platform, an online community forum, chat rooms, Medium publications, and local organizations that intend to make learning web development accessible to anyone.",
      "highlights": [
        "Achieved “Front-end Development Certification” from freeCodeCamp.",
        "Created several projects to achieve the certification which hosted at https://codepen.io/gilangmlr"
      ]
    },
    {
      "organization": "BETIS",
      "position": "Math Tutor",
      "startDate": "2016-04-01",
      "endDate": "2016-05-01",
      "summary": "BETIS (Bimbingan Belajar Gratis) is a free tutoring program from BEM Fasilkom UI for high school students or equivalent to prepare for national college entrance examination (SBMPTN).",
      "highlights": [
        "Helped students solved math problems."
      ]
    }
  ],
  "education": [
    {
      "institution": "Universitas Indonesia",
      "area": "Computer Science",
      "studyType": "Bachelor",
      "startDate": "2015-07-01",
      "endDate": "2019-07-01",
      "gpa": "3.24",
      "courses": []
    }
  ],
  "awards": [],
  "publications": [],
  "skills": [
    {
      "name": "JavaScript",
      "level": "",
      "keywords": [
        "Vue.js",
        "VueX",
        "ReactJS",
        "Redux",
        "Node.js",
        "Express.js",
        "Jest",
        "TypeScript"
      ]
    },
    {
      "name": "Back-end",
      "level": "",
      "keywords": [
        "Python",
        "Django",
        "Django REST framework",
        "Flask",
        "PostgreSQL",
        "SQL"
      ]
    },
    {
      "name": "DevOps",
      "level": "",
      "keywords": [
        "Docker",
        "Kuberrnetes",
        "AWS",
        "Kops (Kubernetes Operations)",
        "Gitlab CI/CD"
      ]
    },
    {
      "name": "Others",
      "level": "",
      "keywords": [
        "Java",
        "GIT",
        "C++",
        "WebGL",
        "Machine Learning"
      ]
    }
  ],
  "languages": [
    {
      "language": "Indonesian",
      "fluency": "Native proficiency"
    },
    {
      "language": "English",
      "fluency": "Professional working proficiency"
    }
  ],
  "interests": [],
  "references": []
}